CFSession/__init__.py
CFSession/__init__.pyi
CFSession/__version__.py
CFSession/cf.py
CFSession/cfbrowser.py
CFSession/cfbrowser.pyi
CFSession/cfcookie.py
CFSession/cfdefaults.py
CFSession/cfdirmodel.py
CFSession/cfdirmodel.pyi
CFSession/cfexception.py
CFSession/cfmodels.py
CFSession/cfmodels.pyi
CFSession/cftoolkit.py
CFSession/py.typed
CFSession-1.5.0.dist-info/LICENSE
CFSession-1.5.0.dist-info/METADATA
CFSession-1.5.0.dist-info/WHEEL
CFSession-1.5.0.dist-info/top_level.txt
CFSession-1.5.0.dist-info/RECORD
