Metadata-Version: 2.1
Name: CFSession
Version: 1.5.0
Summary: A python based IUAM bypasser
Author-email: Kinuseka <support@kinuseka.us>
License: Apache License
Project-URL: homepage, https://github.com/CFSession/CFSession
Keywords: cloudflare,cloudflare-bypass,python,selenium
Classifier: Development Status :: 4 - Beta
Classifier: Programming Language :: Python :: 3
Classifier: Programming Language :: Python :: 3.6
Classifier: Programming Language :: Python :: 3.7
Classifier: Programming Language :: Python :: 3.8
Classifier: Programming Language :: Python :: 3.9
Classifier: Programming Language :: Python :: 3.10
Classifier: License :: OSI Approved :: Apache Software License
Classifier: Operating System :: OS Independent
Classifier: Operating System :: Microsoft :: Windows
Classifier: Operating System :: POSIX :: Linux
Classifier: Operating System :: MacOS
Classifier: Intended Audience :: Developers
Classifier: Topic :: Internet :: WWW/HTTP
Classifier: Typing :: Typed
Requires-Python: >=3.6
License-File: LICENSE
Requires-Dist: requests >=2.25.0
Requires-Dist: undetected-chromedriver !=3.5.1,>=3.5.4
Requires-Dist: loguru ==0.7.2
Requires-Dist: selenium >=4.10.0
Requires-Dist: typing-extensions
Requires-Dist: selenium-wire >=5.1.0
